Workbook
Name SegmentaciónDeDatos_category: #N/A
Name SegmentaciónDeDatos_mes: #N/A

Sheet riesgo_almacen
A1: almacen | B1: productos | C1: bajo_minimo | D1: pct_bajo_minimo
A2: MAD | B2: 2563 | C2: 323 | D2: 0.12602419
A3: BCN | B3: 2513 | C3: 347 | D3: 0.13808197
A4: SVQ | B4: 2464 | C4: 315 | D4: 0.12784091
A5: BIO | B5: 2421 | C5: 261 | D5: 0.10780669
A6: VLC | B6: 2464 | C6: 294 | D6: 0.11931818

Sheet Proveedores
A1: categoria | B1: proveedor | C1: plazo_dias | D1: coste_pct
A2: fasteners | B2: Tornillería Ibérica SL | C2: 10 | D2: 0.5
A3: anchors | B3: Fijaciones Norte SA | C3: 14 | D3: 0.55
A4: hand-tools | B4: Herramientas Levante SL | C4: 21 | D4: 0.6
A5: power-tools | B5: PowerTech Distribución SA | C5: 30 | D5: 0.7
A6: safety | B6: Protección Laboral SL | C6: 14 | D6: 0.55
A7: locks | B7: Cerrajería Central SA | C7: 21 | D7: 0.6
A8: abrasives | B8: Abrasivos del Sur SL | C8: 7 | D8: 0.45
A9: electrical | B9: Material Eléctrico Ebro SL | C9: 10 | D9: 0.5

Sheet pedidos_mensuales
A1: mes | B1: mode | C1: pedidos | D1: ticket_medio | E1: facturacion
A2: 45931 | B2: biz | C2: 156 | D2: 2063.35 | E2: 321882.84
A3: 45931 | B3: diy | C3: 202 | D3: 242.61 | E3: 49007.18
A4: 45962 | B4: biz | C4: 216 | D4: 2588.07 | E4: 559023.58
A5: 45962 | B5: diy | C5: 278 | D5: 296.39 | E5: 82397.07
A6: 45992 | B6: biz | C6: 227 | D6: 1901.46 | E6: 431631.34
A7: 45992 | B7: diy | C7: 261 | D7: 234.29 | E7: 61150.57
A8: 46023 | B8: biz | C8: 194 | D8: 2123.74 | E8: 412005.41
A9: 46023 | B9: diy | C9: 267 | D9: 246.03 | E9: 65689.43
A10: 46054 | B10: biz | C10: 200 | D10: 2282.29 | E10: 456457.96
A11: 46054 | B11: diy | C11: 250 | D11: 225.97 | E11: 56492
A12: 46082 | B12: biz | C12: 197 | D12: 2461.92 | E12: 484998.37
A13: 46082 | B13: diy | C13: 266 | D13: 227.2 | E13: 60436.4
... A27: 46296 | B27: diy | C27: 92 | D27: 223.27 | E27: 20541.05

Sheet ventas_mensuales
A1: mes | B1: category | C1: channel | D1: unidades | E1: ingresos_netos
A2: October | B2: abrasives | C2: b2b | D2: 3940 | E2: 67203.14
A3: October | B3: abrasives | C3: marketplace | D3: 510 | E3: 10256.99
A4: October | B4: abrasives | C4: web | D4: 2124 | E4: 41200.49
A5: October | B5: anchors | C5: b2b | D5: 3145 | E5: 94206.18
A6: October | B6: anchors | C6: marketplace | D6: 447 | E6: 12938.34
A7: October | B7: anchors | C7: web | D7: 1504 | E7: 39503.19
A8: October | B8: electrical | C8: b2b | D8: 3979 | E8: 63642.26
A9: October | B9: electrical | C9: marketplace | D9: 466 | E9: 8831.81
A10: October | B10: electrical | C10: web | D10: 1930 | E10: 33034.4
A11: October | B11: fasteners | C11: b2b | D11: 24918 | E11: 688543.36
A12: October | B12: fasteners | C12: marketplace | D12: 3207 | E12: 97247.93
A13: October | B13: fasteners | C13: web | D13: 12759 | E13: 377073.66
... A313: October | B313: safety | C313: web | D313: 995 | E313: 24457.22

Sheet ventas_90d
A1: sku | B1: unidades_netas_90d | C1: ingresos_netos_90d
A2: SF-933-ZN-4x40-P20 | B2: 17 | C2: 44.96
A3: SF-931-HG-8x40 | B3: 9 | C3: 208.44
A4: SF-AGL-A2-4x25-B1000 | B4: 45 | C4: 855.75
A5: SF-ARD-ALP-A4-16x320 | B5: 67 | C5: 23406.93
A6: SF-934-A2-10-P10 | B6: 40 | C6: 147.18
A7: SF-912-A2-12x25-P10 | B7: 8 | C7: 64.72
A8: SF-933-ZN-8x65 | B8: 9 | C8: 200.22
A9: SF-AGL-ZY-4.5x30-P25 | B9: 25 | C9: 33.89
A10: SF-315-A2-12 | B10: 5 | C10: 104.19
A11: SF-AGL-A2-5x40-B1000 | B11: 35 | C11: 1256.56
A12: SF-AGL-A2-3x40-P25 | B12: 25 | C12: 35.75
A13: SF-933-ZN-14x70 | B13: 21 | C13: 289.82
... A5082: SF-912-ZN-5x8 | B5082: 16 | C5082: 107.66

Sheet stock_actual
A1: Stock_por_SKU | B1: name | C1: category | D1: price_ex_vat | E1: Disponible | F1: unidades_netas_90d | G1: ingresos_netos_90d | H1: proveedor | I1: plazo_dias | J1: coste_pct | K1: ventas_diarias | L1: dias_cobertura | M1: stock_objetivo | N1: unidades_a_pedir | O1: coste_pedido | P1: estado | Q1: valor_stock
A2: SF-TCS-A2-10x160 | B2: Timber construction screw TX50 Ø10 × 160 mm A2 stainless | C2: fasteners | D2: 806.4 | E2: 603 | F2: 104 | G2: 78962.82 | H2: Tornillería Ibérica SL | I2: 10 | J2: 0.5 | K2: 1.1555556 | L2: 521.82692 | M2: 46.222222 | N2: 0 | O2: 0 | P2: SOBRESTOCK | Q2: 243129.6
A3: SF-TCS-A2-6x120 | B3: Timber construction screw TX30 Ø6 × 120 mm A2 stainless | C3: fasteners | D3: 435.46 | E3: 17 | F3: 182 | G3: 74271.6 | H3: Tornillería Ibérica SL | I3: 10 | J3: 0.5 | K3: 2.0222222 | L3: 8.4065934 | M3: 80.888889 | N3: 64 | O3: 13934.72 | P3: PEDIR YA | Q3: 3701.41
A4: SF-TCS-A2-8x120 | B4: Timber construction screw TX40 Ø8 × 120 mm A2 stainless | C4: fasteners | D4: 387.07 | E4: 589 | F4: 178 | G4: 65135.56 | H4: Tornillería Ibérica SL | I4: 10 | J4: 0.5 | K4: 1.9777778 | L4: 297.80899 | M4: 79.111111 | N4: 0 | O4: 0 | P4: SOBRESTOCK | Q4: 113992.12
A5: SF-933-A4-12x60 | B5: Hex bolt DIN 933 M12 × 60 mm A4 stainless | C5: fasteners | D5: 133.1 | E5: 784 | F5: 513 | G5: 57101.11 | H5: Tornillería Ibérica SL | I5: 10 | J5: 0.5 | K5: 5.7 | L5: 137.54386 | M5: 228 | N5: 0 | O5: 0 | P5: OK | Q5: 52175.2
A6: SF-TCS-A2-6x160 | B6: Timber construction screw TX30 Ø6 × 160 mm A2 stainless | C6: fasteners | D6: 580.61 | E6: 1747 | F6: 87 | G6: 48364.78 | H6: Tornillería Ibérica SL | I6: 10 | J6: 0.5 | K6: 0.96666667 | L6: 1807.2414 | M6: 38.666667 | N6: 0 | O6: 0 | P6: SOBRESTOCK | Q6: 507162.84
A7: SF-TCS-ZY-10x400 | B7: Timber construction screw TX50 Ø10 × 400 mm yellow zinc | C7: fasteners | D7: 840 | E7: 0 | F7: 53 | G7: 43915.2 | H7: Tornillería Ibérica SL | I7: 10 | J7: 0.5 | K7: 0.58888889 | L7: 0 | M7: 23.555556 | N7: 24 | O7: 10080 | P7: ROTO | Q7: 0
A8: SF-TCS-ZY-10x280 | B8: Timber construction screw TX50 Ø10 × 280 mm yellow zinc | C8: fasteners | D8: 588 | E8: 2159 | F8: 71 | G8: 39631.2 | H8: Tornillería Ibérica SL | I8: 10 | J8: 0.5 | K8: 0.78888889 | L8: 2736.7606 | M8: 31.555556 | N8: 0 | O8: 0 | P8: SOBRESTOCK | Q8: 634746
A9: SF-TCS-ZY-10x180 | B9: Timber construction screw TX50 Ø10 × 180 mm yellow zinc | C9: fasteners | D9: 378 | E9: 201 | F9: 109 | G9: 39054.96 | H9: Tornillería Ibérica SL | I9: 10 | J9: 0.5 | K9: 1.2111111 | L9: 165.9633 | M9: 48.444444 | N9: 0 | O9: 0 | P9: OK | Q9: 37989
A10: SF-TCS-A2-6x180 | B10: Timber construction screw TX30 Ø6 × 180 mm A2 stainless | C10: fasteners | D10: 653.18 | E10: 1658 | F10: 61 | G10: 38211.18 | H10: Tornillería Ibérica SL | I10: 10 | J10: 0.5 | K10: 0.67777778 | L10: 2446.2295 | M10: 27.111111 | N10: 0 | O10: 0 | P10: SOBRESTOCK | Q10: 541486.22
A11: SF-933-A4-10x60 | B11: Hex bolt DIN 933 M10 × 60 mm A4 stainless | C11: fasteners | D11: 101.3 | E11: 407 | F11: 383 | G11: 36922.9 | H11: Tornillería Ibérica SL | I11: 10 | J11: 0.5 | K11: 4.2555556 | L11: 95.639687 | M11: 170.22222 | N11: 0 | O11: 0 | P11: OK | Q11: 20614.55
A12: SF-7991-A2-10x80-B500 | B12: Countersunk socket screw DIN 7991 M10 × 80 mm A2 stainless, bulk box of 500 | C12: fasteners | D12: 357.76 | E12: 1128 | F12: 109 | G12: 36734.88 | H12: Tornillería Ibérica SL | I12: 10 | J12: 0.5 | K12: 1.2111111 | L12: 931.37615 | M12: 48.444444 | N12: 0 | O12: 0 | P12: SOBRESTOCK | Q12: 201776.64
A13: SF-TCS-A2-10x200 | B13: Timber construction screw TX50 Ø10 × 200 mm A2 stainless | C13: fasteners | D13: 1008 | E13: 542 | F13: 33 | G13: 32739.84 | H13: Tornillería Ibérica SL | I13: 10 | J13: 0.5 | K13: 0.36666667 | L13: 1478.1818 | M13: 14.666667 | N13: 0 | O13: 0 | P13: SOBRESTOCK | Q13: 273168
... A4901: SF-AGL-ZY-3x50-P25 | B4901: Chipboard screw, Pozidriv Ø3 × 50 mm yellow zinc, pack of 25 | C4901: fasteners | D4901: 1.39 | E4901: 833 | F4901: 1 | G4901: 1.25 | H4901: Tornillería Ibérica SL | I4901: 10 | J4901: 0.5 | K4901: 0.011111111 | L4901: 74970 | M4901: 0.44444444 | N4901: 0 | O4901: 0 | P4901: SOBRESTOCK | Q4901: 578.935
A4902: SF-7991-A2-6x75-B500 | B4902: Countersunk socket screw DIN 7991 M6 × 75 mm A2 stainless, bulk box of 500 | C4902: fasteners | D4902: 157.81 | E4902: 1218 | F4902: 0 | G4902: 0 | H4902: Tornillería Ibérica SL | I4902: 10 | J4902: 0.5 | K4902: 0 | L4902: #NUM! | M4902: 0 | N4902: 0 | O4902: 0 | P4902: STOCK MUERTO | Q4902: 96106.29
A4903: SF-933-A4-6x120 | B4903: Hex bolt DIN 933 M6 × 120 mm A4 stainless | C4903: fasteners | D4903: 83.7 | E4903: 1539 | F4903: 0 | G4903: 0 | H4903: Tornillería Ibérica SL | I4903: 10 | J4903: 0.5 | K4903: 0 | L4903: #NUM! | M4903: 0 | N4903: 0 | O4903: 0 | P4903: STOCK MUERTO | Q4903: 64407.15
A4904: SF-912-A4-3x12 | B4904: Socket cap screw DIN 912 M3 × 12 mm A4 stainless | C4904: fasteners | D4904: 10.4 | E4904: 2179 | F4904: 0 | G4904: 0 | H4904: Tornillería Ibérica SL | I4904: 10 | J4904: 0.5 | K4904: 0 | L4904: #NUM! | M4904: 0 | N4904: 0 | O4904: 0 | P4904: STOCK MUERTO | Q4904: 11330.8
A4905: SF-AGL-A2-3x40 | B4905: Chipboard screw, Pozidriv Ø3 × 40 mm A2 stainless | C4905: fasteners | D4905: 4 | E4905: 6 | F4905: 0 | G4905: 0 | H4905: Tornillería Ibérica SL | I4905: 10 | J4905: 0.5 | K4905: 0 | L4905: #NUM! | M4905: 0 | N4905: 0 | O4905: 0 | P4905: STOCK MUERTO | Q4905: 12
A4906: SF-912-A4-16x30 | B4906: Socket cap screw DIN 912 M16 × 30 mm A4 stainless | C4906: fasteners | D4906: 25.68 | E4906: 1367 | F4906: 0 | G4906: 0 | H4906: Tornillería Ibérica SL | I4906: 10 | J4906: 0.5 | K4906: 0 | L4906: #NUM! | M4906: 0 | N4906: 0 | O4906: 0 | P4906: STOCK MUERTO | Q4906: 17552.28
A4907: SF-UNP-TAT-10x50-P20 | B4907: Tatra Works universal plug for all substrates 10 × 50 mm, pack of 20 | C4907: anchors | D4907: 4.39 | E4907: 1227 | F4907: 0 | G4907: 0 | H4907: Fijaciones Norte SA | I4907: 14 | J4907: 0.55 | K4907: 0 | L4907: #NUM! | M4907: 0 | N4907: 0 | O4907: 0 | P4907: STOCK MUERTO | Q4907: 2962.5915
A4908: SF-976-A4-12x500 | B4908: Threaded rod DIN 976 M12 × 500 mm A4 stainless | C4908: fasteners | D4908: 10.09 | E4908: 1675 | F4908: 0 | G4908: 0 | H4908: Tornillería Ibérica SL | I4908: 10 | J4908: 0.5 | K4908: 0 | L4908: #NUM! | M4908: 0 | N4908: 0 | O4908: 0 | P4908: STOCK MUERTO | Q4908: 8450.375
A4909: SF-AGL-ZY-6x35-P25 | B4909: Chipboard screw, Pozidriv Ø6 × 35 mm yellow zinc, pack of 25 | C4909: fasteners | D4909: 2.29 | E4909: 1950 | F4909: 0 | G4909: 0 | H4909: Tornillería Ibérica SL | I4909: 10 | J4909: 0.5 | K4909: 0 | L4909: #NUM! | M4909: 0 | N4909: 0 | O4909: 0 | P4909: STOCK MUERTO | Q4909: 2232.75
A4910: SF-AGL-ZY-4.5x50-B1000 | B4910: Chipboard screw, Pozidriv Ø4.5 × 50 mm yellow zinc, bulk box of 1000 | C4910: fasteners | D4910: 15.05 | E4910: 1879 | F4910: 0 | G4910: 0 | H4910: Tornillería Ibérica SL | I4910: 10 | J4910: 0.5 | K4910: 0 | L4910: #NUM! | M4910: 0 | N4910: 0 | O4910: 0 | P4910: STOCK MUERTO | Q4910: 14139.475
A4911: SF-7991-ZN-16x100 | B4911: Countersunk socket screw DIN 7991 M16 × 100 mm zinc plated | C4911: fasteners | D4911: 21.33 | E4911: 1463 | F4911: 0 | G4911: 0 | H4911: Tornillería Ibérica SL | I4911: 10 | J4911: 0.5 | K4911: 0 | L4911: #NUM! | M4911: 0 | N4911: 0 | O4911: 0 | P4911: STOCK MUERTO | Q4911: 15602.895
A4912: SF-7991-ZN-8x100 | B4912: Countersunk socket screw DIN 7991 M8 × 100 mm zinc plated | C4912: fasteners | D4912: 15.05 | E4912: 1124 | F4912: 0 | G4912: 0 | H4912: Tornillería Ibérica SL | I4912: 10 | J4912: 0.5 | K4912: 0 | L4912: #NUM! | M4912: 0 | N4912: 0 | O4912: 0 | P4912: STOCK MUERTO | Q4912: 8458.1
A4913: SF-933-A4-8x70 | B4913: Hex bolt DIN 933 M8 × 70 mm A4 stainless | C4913: fasteners | D4913: 81.9 | E4913: 1135 | F4913: 0 | G4913: 0 | H4913: Tornillería Ibérica SL | I4913: 10 | J4913: 0.5 | N4913: 0 | O4913: 0 | P4913: STOCK MUERTO | Q4913: 46478.25
A4914: SF-933-A4-24x60 | B4914: Hex bolt DIN 933 M24 × 60 mm A4 stainless | C4914: fasteners | D4914: 37.66 | E4914: 2095 | F4914: 0 | G4914: 0 | H4914: Tornillería Ibérica SL | I4914: 10 | J4914: 0.5 | N4914: 0 | O4914: 0 | P4914: STOCK MUERTO | Q4914: 39448.85
A4915: SF-933-A4-14x90 | B4915: Hex bolt DIN 933 M14 × 90 mm A4 stainless | C4915: fasteners | D4915: 58.25 | E4915: 1483 | F4915: 0 | G4915: 0 | H4915: Tornillería Ibérica SL | I4915: 10 | J4915: 0.5 | N4915: 0 | O4915: 0 | P4915: STOCK MUERTO | Q4915: 43192.375
A4916: SF-933-A4-12x50 | B4916: Hex bolt DIN 933 M12 × 50 mm A4 stainless | C4916: fasteners | D4916: 57.95 | E4916: 1727 | F4916: 0 | G4916: 0 | H4916: Tornillería Ibérica SL | I4916: 10 | J4916: 0.5 | N4916: 0 | O4916: 0 | P4916: STOCK MUERTO | Q4916: 50039.825
A4917: SF-933-A2-4x35 | B4917: Hex bolt DIN 933 M4 × 35 mm A2 stainless | C4917: fasteners | D4917: 12.5 | E4917: 13 | F4917: 0 | G4917: 0 | H4917: Tornillería Ibérica SL | I4917: 10 | J4917: 0.5 | N4917: 0 | O4917: 0 | P4917: STOCK MUERTO | Q4917: 81.25
A4918: SF-933-A2-8x40-P10 | B4918: Hex bolt DIN 933 M8 × 40 mm A2 stainless, pack of 10 | C4918: fasteners | D4918: 7.99 | E4918: 1425 | F4918: 0 | G4918: 0 | H4918: Tornillería Ibérica SL | I4918: 10 | J4918: 0.5 | N4918: 0 | O4918: 0 | P4918: STOCK MUERTO | Q4918: 5692.875
A4919: SF-933-ZN-4x20 | B4919: Hex bolt DIN 933 M4 × 20 mm zinc plated | C4919: fasteners | D4919: 7.6 | E4919: 1390 | F4919: 0 | G4919: 0 | H4919: Tornillería Ibérica SL | I4919: 10 | J4919: 0.5 | N4919: 0 | O4919: 0 | P4919: STOCK MUERTO | Q4919: 5282
A4920: SF-933-A2-12x100-P10 | B4920: Hex bolt DIN 933 M12 × 100 mm A2 stainless, pack of 10 | C4920: fasteners | D4920: 28.39 | E4920: 509 | F4920: 0 | G4920: 0 | H4920: Tornillería Ibérica SL | I4920: 10 | J4920: 0.5 | N4920: 0 | O4920: 0 | P4920: STOCK MUERTO | Q4920: 7225.255
A4921: SF-931-ZN-8x60-P10 | B4921: Hex bolt part thread DIN 931 M8 × 60 mm zinc plated, pack of 10 | C4921: fasteners | D4921: 5.09 | E4921: 484 | F4921: 0 | G4921: 0 | H4921: Tornillería Ibérica SL | I4921: 10 | J4921: 0.5 | N4921: 0 | O4921: 0 | P4921: STOCK MUERTO | Q4921: 1231.78
A4922: SF-933-A2-8x45-B500 | B4922: Hex bolt DIN 933 M8 × 45 mm A2 stainless, bulk box of 500 | C4922: fasteners | D4922: 181.89 | E4922: 2222 | F4922: 0 | G4922: 0 | H4922: Tornillería Ibérica SL | I4922: 10 | J4922: 0.5 | N4922: 0 | O4922: 0 | P4922: STOCK MUERTO | Q4922: 202079.79
A4923: SF-976-A2-6x2000 | B4923: Threaded rod DIN 976 M6 × 2000 mm A2 stainless | C4923: fasteners | D4923: 7.99 | E4923: 853 | F4923: 0 | G4923: 0 | H4923: Tornillería Ibérica SL | I4923: 10 | J4923: 0.5 | N4923: 0 | O4923: 0 | P4923: STOCK MUERTO | Q4923: 3407.735
A4924: SF-AGL-A2-5x25-B1000 | B4924: Chipboard screw, Pozidriv Ø5 × 25 mm A2 stainless, bulk box of 1000 | C4924: fasteners | D4924: 30.1 | E4924: 1731 | F4924: 0 | G4924: 0 | H4924: Tornillería Ibérica SL | I4924: 10 | J4924: 0.5 | N4924: 0 | O4924: 0 | P4924: STOCK MUERTO | Q4924: 26051.55
... A4963: SF-WDG-TAT-ZN-8x75 | B4963: Tatra Works wedge anchor M8 × 75 mm, zinc plated | C4963: anchors | D4963: 29.89 | E4963: 1378 | F4963: 0 | G4963: 0 | H4963: Fijaciones Norte SA | I4963: 14 | J4963: 0.55 | N4963: 0 | O4963: 0 | P4963: STOCK MUERTO | Q4963: 22653.631

Sheet dashboard
B2: Shopping Cart Value | E2: Dead Stock Value | G2: Dead stock value over total value | J2: SALES PER CATEGORY AND MONTH
B4: ='1.Lista de la compra'!C455 -> 164375.67 | E4: ='2.stock muerto'!A2 -> 1020341 | G4: ='2.stock muerto'!C2 -> 0.013498668
B9: percentage of minimum stock per warehouse | E9: ABC products and percentage
B10: Warehouse | C10: Percentage of min | E10: Class | F10: Stock per SKU | G10: Total of turnover
B11: BCN | C11: 0.13808197 | E11: Clase A | F11: 0.19951632 | G11: 4579850.6
B12: BIO | C12: 0.10780669 | E12: Clase B | F12: 0.26541717 | G12: 858826.93
B13: MAD | C13: 0.12602419 | E13: Clase C | F13: 0.53506651 | G13: 286264.1
B14: SVQ | C14: 0.12784091
B15: VLC | C15: 0.11931818
O16: mes | P16: (Todas)
B17: SKU SEARCH | C17: Stock | D17: Coverage (days) | E17: State
B18: SF-125-A2-10-P20 | C18: =_xlfn.XLOOKUP(B18,stock_actual!A:A,stock_actual!E:E,"Insertar SKU válido",0) -> 1750 | D18: =_xlfn.XLOOKUP(B18,stock_actual!A:A,stock_actual!L:L,"Ingresar SKU válido",0) -> 78750 | E18: =_xlfn.XLOOKUP(B18,stock_actual!A:A,stock_actual!P:P,"Ingresar SKU válido",0) -> SOBRESTOCK | O18: Etiquetas de fila | P18: Suma de unidades
O19: abrasives | P19: 150313
O20: anchors | P20: 121443
O21: electrical | P21: 141920
O22: fasteners | P22: 917078
O23: hand-tools | P23: 296749
O24: locks | P24: 111997
O25: power-tools | P25: 52754
O26: safety | P26: 148060
O27: Total general | P27: 1940314

Sheet 1.Lista de la compra
A1: estado | B1: (Varios elementos)
A3: Stock_por_SKU | B3: name | C3: Suma de coste_pedido | D3: Suma de unidades_a_pedir
A4: SF-TCS-A2-6x120 | B4: Timber construction screw TX30 Ø6 × 120 mm A2 stainless | C4: 13934.72 | D4: 64
A5: SF-TCS-ZY-10x400 | B5: Timber construction screw TX50 Ø10 × 400 mm yellow zinc | C5: 10080 | D5: 24
A6: SF-912-A2-8x55-B500 | B6: Socket cap screw DIN 912 M8 × 55 mm A2 stainless, bulk box of 500 | C6: 6325.085 | D6: 73
A7: SF-912-A2-10x40-B500 | B7: Socket cap screw DIN 912 M10 × 40 mm A2 stainless, bulk box of 500 | C7: 4410.94 | D7: 46
A8: SF-912-A2-6x60-B500 | B8: Socket cap screw DIN 912 M6 × 60 mm A2 stainless, bulk box of 500 | C8: 4334.4 | D8: 72
A9: SF-933-A2-10x25 | B9: Hex bolt DIN 933 M10 × 25 mm A2 stainless | C9: 3468.65 | D9: 173
A10: SF-ARD-ALP-ZN-20x400 | B10: Alpenfix anchor rod M20 × 400 mm, zinc plated, pack of 10 | C10: 3461.3865 | D10: 27
A11: SF-933-ZN-12x40 | B11: Hex bolt DIN 933 M12 × 40 mm zinc plated | C11: 2835 | D11: 189
A12: SF-912-BK-10x40 | B12: Socket cap screw DIN 912 M10 × 40 mm black 12.9 | C12: 2707.25 | D12: 221
A13: SF-933-ZN-8x75-B500 | B13: Hex bolt DIN 933 M8 × 75 mm zinc plated, bulk box of 500 | C13: 2601.07 | D13: 46
A14: SF-933-A4-10x25 | B14: Hex bolt DIN 933 M10 × 25 mm A4 stainless | C14: 2543.8 | D14: 92
A15: SF-931-A4-20x160 | B15: Hex bolt part thread DIN 931 M20 × 160 mm A4 stainless | C15: 2266.225 | D15: 65
... A454: SF-127-ZN-12-P20 | B454: Spring washer DIN 127 M12 zinc plated, pack of 20 | C454: 0 | D454: 0
A455: Total general | C455: 164375.67 | D455: 11221

Sheet 4. crear abc
A1: Stock_por_SKU | B1: name | C1: category | D1: ingresos_netos_90d | E1: valor acumulado | F1: porcentajer acumulado | G1: ABC | I1: valor acumulado total | J1: =SUM(D:D) -> 5724941.6
A2: SF-TCS-A2-10x160 | B2: Timber construction screw TX50 Ø10 × 160 mm A2 stainless | C2: fasteners | D2: 78962.82 | E2: =SUM($D$2:D2) -> 78962.82 | F2: =E2/$J$1 -> 0.013792773 | G2: {=_xlfn.IFS(F2<0.8,"Clase A",F2<0.95,"Clase B",F2>=0.95,"Clase C")} -> Clase A
A3: SF-TCS-A2-6x120 | B3: Timber construction screw TX30 Ø6 × 120 mm A2 stainless | C3: fasteners | D3: 74271.6 | E3: =SUM($D$2:D3) -> 153234.42 | F3: =E3/$J$1 -> 0.02676611 | G3: {=_xlfn.IFS(F3<0.8,"Clase A",F3<0.95,"Clase B",F3>=0.95,"Clase C")} -> Clase A
A4: SF-TCS-A2-8x120 | B4: Timber construction screw TX40 Ø8 × 120 mm A2 stainless | C4: fasteners | D4: 65135.56 | E4: =SUM($D$2:D4) -> 218369.98 | F4: =E4/$J$1 -> 0.038143617 | G4: {=_xlfn.IFS(F4<0.8,"Clase A",F4<0.95,"Clase B",F4>=0.95,"Clase C")} -> Clase A
A5: SF-933-A4-12x60 | B5: Hex bolt DIN 933 M12 × 60 mm A4 stainless | C5: fasteners | D5: 57101.11 | E5: =SUM($D$2:D5) -> 275471.09 | F5: =E5/$J$1 -> 0.048117712 | G5: {=_xlfn.IFS(F5<0.8,"Clase A",F5<0.95,"Clase B",F5>=0.95,"Clase C")} -> Clase A
A6: SF-TCS-A2-6x160 | B6: Timber construction screw TX30 Ø6 × 160 mm A2 stainless | C6: fasteners | D6: 48364.78 | E6: =SUM($D$2:D6) -> 323835.87 | F6: =E6/$J$1 -> 0.056565794 | G6: {=_xlfn.IFS(F6<0.8,"Clase A",F6<0.95,"Clase B",F6>=0.95,"Clase C")} -> Clase A
A7: SF-TCS-ZY-10x400 | B7: Timber construction screw TX50 Ø10 × 400 mm yellow zinc | C7: fasteners | D7: 43915.2 | E7: =SUM($D$2:D7) -> 367751.07 | F7: =E7/$J$1 -> 0.06423665 | G7: {=_xlfn.IFS(F7<0.8,"Clase A",F7<0.95,"Clase B",F7>=0.95,"Clase C")} -> Clase A
A8: SF-TCS-ZY-10x280 | B8: Timber construction screw TX50 Ø10 × 280 mm yellow zinc | C8: fasteners | D8: 39631.2 | E8: =SUM($D$2:D8) -> 407382.27 | F8: =E8/$J$1 -> 0.071159201 | G8: {=_xlfn.IFS(F8<0.8,"Clase A",F8<0.95,"Clase B",F8>=0.95,"Clase C")} -> Clase A
A9: SF-TCS-ZY-10x180 | B9: Timber construction screw TX50 Ø10 × 180 mm yellow zinc | C9: fasteners | D9: 39054.96 | E9: =SUM($D$2:D9) -> 446437.23 | F9: =E9/$J$1 -> 0.077981097 | G9: {=_xlfn.IFS(F9<0.8,"Clase A",F9<0.95,"Clase B",F9>=0.95,"Clase C")} -> Clase A
A10: SF-TCS-A2-6x180 | B10: Timber construction screw TX30 Ø6 × 180 mm A2 stainless | C10: fasteners | D10: 38211.18 | E10: =SUM($D$2:D10) -> 484648.41 | F10: =E10/$J$1 -> 0.084655607 | G10: {=_xlfn.IFS(F10<0.8,"Clase A",F10<0.95,"Clase B",F10>=0.95,"Clase C")} -> Clase A
A11: SF-933-A4-10x60 | B11: Hex bolt DIN 933 M10 × 60 mm A4 stainless | C11: fasteners | D11: 36922.9 | E11: =SUM($D$2:D11) -> 521571.31 | F11: =E11/$J$1 -> 0.091105088 | G11: {=_xlfn.IFS(F11<0.8,"Clase A",F11<0.95,"Clase B",F11>=0.95,"Clase C")} -> Clase A
A12: SF-7991-A2-10x80-B500 | B12: Countersunk socket screw DIN 7991 M10 × 80 mm A2 stainless, bulk box of 500 | C12: fasteners | D12: 36734.88 | E12: =SUM($D$2:D12) -> 558306.19 | F12: =E12/$J$1 -> 0.097521726 | G12: {=_xlfn.IFS(F12<0.8,"Clase A",F12<0.95,"Clase B",F12>=0.95,"Clase C")} -> Clase A
A13: SF-TCS-A2-10x200 | B13: Timber construction screw TX50 Ø10 × 200 mm A2 stainless | C13: fasteners | D13: 32739.84 | E13: =SUM($D$2:D13) -> 591046.03 | F13: =E13/$J$1 -> 0.10324053 | G13: {=_xlfn.IFS(F13<0.8,"Clase A",F13<0.95,"Clase B",F13>=0.95,"Clase C")} -> Clase A
... A4963: SF-WDG-TAT-ZN-8x75 | B4963: Tatra Works wedge anchor M8 × 75 mm, zinc plated | C4963: anchors | D4963: 0 | E4963: =SUM($D$2:D4963) -> 5724941.6 | F4963: =E4963/$J$1 -> 1 | G4963: {=_xlfn.IFS(F4963<0.8,"Clase A",F4963<0.95,"Clase B",F4963>=0.95,"Clase C")} -> Clase C

Sheet 2.stock muerto
A1: valor stock muerto | B1: valor stock | C1: porcentaje de stock muerto
A2: =SUMIFS(stock_actual!Q:Q,stock_actual!P:P,"STOCK MUERTO") -> 1020341 | B2: =SUM(stock_actual!Q:Q) -> 75588269 | C2: =A2/B2 -> 0.013498668
